pylw/__init__.py
pylw/app.py
pylw/app.so
pylw/hello.so
pylw/qs_parse.so
pylw/request.py
pylw/request.so
pylw/resource.py
pylw/resource.so
pylw/response.py
pylw/response.so
pylw/route_find.so
pylw/routing.py
pylw/routing.so
pylw-0.1.6.dist-info/DESCRIPTION.rst
pylw-0.1.6.dist-info/METADATA
pylw-0.1.6.dist-info/RECORD
pylw-0.1.6.dist-info/WHEEL
pylw-0.1.6.dist-info/metadata.json
pylw-0.1.6.dist-info/top_level.txt
